libjpg/__init__.py
libjpg/ld-musl-x86_64.so.1
libjpg/libc.musl-x86_64.so.1
libjpg/libjpeg.so
libjpg/libjpeg.so.62
libjpg/libjpeg.so.62.3.0
libjpg/libjpeg.so.8
libjpg/libturbojpeg.so
libjpg/libturbojpeg.so.0
libjpg/libturbojpeg.so.0.2.0
libjpg_bins-0.0.9.dist-info/METADATA
libjpg_bins-0.0.9.dist-info/WHEEL
libjpg_bins-0.0.9.dist-info/top_level.txt
libjpg_bins-0.0.9.dist-info/RECORD
