Metadata-Version: 2.1
Name: libjpg-bins
Version: 0.0.9
Summary: Libraries for LibJPG Turbo on Alpine Linux
Home-page: https://github.com/spencer-hanson/libjpeg-turbo
Author: Spencer Hanson
Author-email: UNKNOWN
License: UNKNOWN
Keywords: libjpg
Platform: UNKNOWN
